[{"rate":2,"positionRate":2,"cleaningRate":2,"serviceRate":2,"priceRate":2,"usernameCreator":"Admin","dateCreation":"03-09-2024 17:18:36","hotelName":"Hotel Aosta 2","hotelCity":"Aosta"},{"rate":2,"positionRate":2,"cleaningRate":2,"serviceRate":2,"priceRate":2,"usernameCreator":"Admin","dateCreation":"03-09-2024 17:33:41","hotelName":"Hotel Roma 2","hotelCity":"Roma"},{"rate":3,"positionRate":3,"cleaningRate":3,"serviceRate":3,"priceRate":3,"usernameCreator":"Admin1","dateCreation":"03-09-2024 17:34:01","hotelName":"Hotel Roma 1","hotelCity":"Roma"},{"rate":4,"positionRate":4,"cleaningRate":4,"serviceRate":4,"priceRate":4,"usernameCreator":"Admin","dateCreation":"03-09-2024 17:34:28","hotelName":"Hotel Roma 4","hotelCity":"Roma"},{"rate":5,"positionRate":4,"cleaningRate":4,"serviceRate":4,"priceRate":4,"usernameCreator":"Admin1","dateCreation":"03-09-2024 17:34:57","hotelName":"Hotel Roma 3","hotelCity":"Roma"},{"rate":5,"positionRate":5,"cleaningRate":5,"serviceRate":5,"priceRate":5,"usernameCreator":"Admin1","dateCreation":"03-09-2024 17:35:34","hotelName":"Hotel Roma 10","hotelCity":"Roma"}]